[
  {
    "name": "Chris",
    "hobby": "Videogames",
    "age": 21,
    "phone": "16654654",
    "address": "In his house 123, Mexico"
  },
  {
    "name": "Javier",
    "hobby": "Running",
    "age": 19,
    "phone": "51651312",
    "address": "New mexico hasuse"
  },
  {
    "name": "Maria",
    "hobby": "Drawing",
    "age": 19,
    "phone": "168449611",
    "address": "Casa mamlona en francia"
  },
  {
    "name": "Andres",
    "hobby": "Valer madres",
    "age": 19,
    "phone": "5684894654",
    "address": "Los pinos"
  }
]
